<?xml version="1.0" encoding="utf-8"?>
<schemalist>
  <schema id="org.gnome.shell.extensions.commontv" path="/org/gnome/shell/extensions/commontv/">
    <key name="padding-inner" type="i">
      <default>8</default>
      <summary>Inner padding</summary>
      <description>Padding between windows</description>
    </key>
    <key name="animate" type="b">
      <default>true</default>
      <summary>Animation</summary>
      <description>Whether to animate window movement/resizing</description>
    </key>
    <key name="convert-to-card" type="as">
      <default>['&lt;Super&gt;c']</default>
      <summary>Convert window to card</summary>
      <description>Keybinding to convert focused window to card view</description>
    </key>
    <key name="convert-to-main" type="as">
      <default>['&lt;Super&gt;m']</default>
      <summary>Convert window to main</summary>
      <description>Keybinding to convert focused window to main view</description>
    </key>
  </schema>
</schemalist>